adaptive_cards/__init__.py
adaptive_cards/actions.py
adaptive_cards/adaptive_card.py
adaptive_cards/containers.py
adaptive_cards/elements.py
adaptive_cards/inputs.py
adaptive_cards/material.py
adaptive_cards_io-1.4.0.dist-info/licenses/LICENSE
adaptive_cards_io-1.4.0.dist-info/METADATA
adaptive_cards_io-1.4.0.dist-info/WHEEL
adaptive_cards_io-1.4.0.dist-info/top_level.txt
adaptive_cards_io-1.4.0.dist-info/RECORD
