Metadata-Version: 2.4
Name: adaptive-cards-io
Version: 1.4.0
Summary: A lightweight framework for building MS adaptive cards programmatically.
Home-page: https://github.com/melquibrito/adaptive-cards
Author: Melqui Brito
Author-email: melquibrito07@gmail.com
Maintainer: Melqui Brito
Maintainer-email: melquibrito07@gmail.com
Classifier: Programming Language :: Python :: 3
Classifier: License :: OSI Approved :: MIT License
Classifier: Operating System :: OS Independent
Requires-Python: >=3.7
License-File: LICENSE
Dynamic: author
Dynamic: author-email
Dynamic: classifier
Dynamic: description
Dynamic: description-content-type
Dynamic: home-page
Dynamic: license-file
Dynamic: maintainer
Dynamic: maintainer-email
Dynamic: requires-python
Dynamic: summary
